validator_docs/__init__.py
validator_docs/validador.py
validador_docs-0.0.1.dist-info/METADATA
validador_docs-0.0.1.dist-info/WHEEL
validador_docs-0.0.1.dist-info/top_level.txt
validador_docs-0.0.1.dist-info/RECORD
