Metadata-Version: 2.1
Name: validador_docs
Version: 0.0.1
Summary: Validators Brasilian documents
Home-page: https://github.com/edmaker89/validator_documents_package
Author: edmaker89
Author-email: edmaker@gmail.com
Requires-Python: >=3.12
